{
  "root": "/data/home/hiroyoshi/semi-final",
  "idx-to-name":"/data/home/hiroyoshi/scripts/meg-mvpa/data/aparc-idx_to_name.pickle",
  "subjects-dir": "/data/home/hiroyoshi/freesurfer/subjects",
  "dir-name": "/data/home/hiroyoshi/semi-final/dataset-dir",
  "df-dir": "/data/home/hiroyoshi/semi-final/param-dir/df-dir",
  "dst-name": "nv",
  "to-index": true,
  "parcellation": "aparc",
  "hemi": "lh",
  "memmap": false,
  "mode": "nv",
  "balance": true,
  "params":
  {
    "number": null,
    "tense": null,
    "person": null,
    "voice": null,
    "finite": false,
    "complex": false,
    "aux": false,
    "ambiguous": false,
    "common": false,
    "diminutive": false,
    "uncountable": false,
    "proper": false
  }

}